MANIFEST.in
PROTOCOLS.md
README.md
setup.py
bin/es-cleantweet
bin/es-managerd.sh
bin/es-meta
bin/es-read
bin/es-rss
bin/es-run
bin/es-service
bin/es-write
eslib/Configurable.py
eslib/Connector.py
eslib/Generator.py
eslib/Monitor.py
eslib/Processor.py
eslib/Socket.py
eslib/Terminal.py
eslib/TerminalInfo.py
eslib/__init__.py
eslib/debug.py
eslib/esdoc.py
eslib/prog.py
eslib/text.py
eslib/time.py
eslib/web.py
eslib.egg-info/PKG-INFO
eslib.egg-info/SOURCES.txt
eslib.egg-info/dependency_links.txt
eslib.egg-info/not-zip-safe
eslib.egg-info/requires.txt
eslib.egg-info/top_level.txt
eslib/procs/BlacklistFilter.py
eslib/procs/CLIReader.py
eslib/procs/CsvConverter.py
eslib/procs/DateExpander.py
eslib/procs/ElasticsearchReader.py
eslib/procs/ElasticsearchWriter.py
eslib/procs/EntityExtractor.py
eslib/procs/FileReader.py
eslib/procs/FileWriter.py
eslib/procs/FourChanMonitor.py
eslib/procs/HtmlRemover.py
eslib/procs/HttpMonitor.py
eslib/procs/KafkaMonitor.py
eslib/procs/KafkaWriter.py
eslib/procs/Neo4jReader.py
eslib/procs/Neo4jWriter.py
eslib/procs/PatternRemover.py
eslib/procs/ProcessWrapper.py
eslib/procs/RabbitmqBase.py
eslib/procs/RabbitmqMonitor.py
eslib/procs/RabbitmqWriter.py
eslib/procs/RssMonitor.py
eslib/procs/SmtpMailer.py
eslib/procs/TcpWriter.py
eslib/procs/Throttle.py
eslib/procs/Timer.py
eslib/procs/Transformer.py
eslib/procs/TweetEntityRemover.py
eslib/procs/TweetExtractor.py
eslib/procs/TwitterFollowerGetter.py
eslib/procs/TwitterMonitor.py
eslib/procs/TwitterUserGetter.py
eslib/procs/WebGetter.py
eslib/procs/__init__.py
eslib/procs/neo4j.py
eslib/procs/twitter.py
eslib/service/Client.py
eslib/service/DummyService.py
eslib/service/HttpService.py
eslib/service/PipelineService.py
eslib/service/RemotingService.py
eslib/service/Service.py
eslib/service/ServiceLauncher.py
eslib/service/ServiceManager.py
eslib/service/UrlParamParser.py
eslib/service/__init__.py
eslib/service/dicthelp.py
examples/entity_extractor.py