Metadata-Version: 1.1
Name: eslib
Version: 0.0.11
Summary: Document processing framework and utility for Elasticsearch (or whatever).
Home-page: https://github.com/comperiosearch/elasticsearch-eslib
Author: Hans Terje Bakke
Author-email: hans.terje.bakke@comperio.no
License: Apache 2.0
Keywords: document processing docproc
Platform: UNKNOWN
Classifier: Development Status :: 5 - Production/Stable
Classifier: Intended Audience :: Developers
Classifier: Natural Language :: English
Classifier: License :: OSI Approved :: Apache Software License
Classifier: Programming Language :: Python
Classifier: Programming Language :: Python :: 2
Classifier: Programming Language :: Python :: 2.7
